metaonnx/__init__.py
metaonnx/app/__init__.py
metaonnx/app/classification.py
metaonnx/app/detection.py
metaonnx/app/face_detection.py
metaonnx/app/face_embedding.py
metaonnx/app/face_recognition.py
metaonnx/app/obb_detection.py
metaonnx/app/person_detection.py
metaonnx/app/segment.py
metaonnx/model_zoo/__init__.py
metaonnx/model_zoo/model.py
metaonnx/utils/__init__.py
meta_onnx-0.1.2.dist-info/METADATA
meta_onnx-0.1.2.dist-info/WHEEL
meta_onnx-0.1.2.dist-info/top_level.txt
meta_onnx-0.1.2.dist-info/zip-safe
meta_onnx-0.1.2.dist-info/RECORD
