Metadata-Version: 2.1
Name: meta-onnx
Version: 0.1.2
Summary: Meta Onnx Toolkit
Home-page: https://github.com/CachCheng/metaonnx
Author: CachCheng
Author-email: tkggpdc2007@163.com
License: Apache-2.0
Platform: UNKNOWN
Requires-Dist: opencv-python
Requires-Dist: setuptools
Requires-Dist: numpy
Requires-Dist: meta-cv
Requires-Dist: onnxruntime
